s3docker/__init__.py
s3docker/cli.py
s3docker/core.py
s3docker/layers.py
s3docker-2.0.2.dist-info/LICENSE.rst
s3docker-2.0.2.dist-info/METADATA
s3docker-2.0.2.dist-info/WHEEL
s3docker-2.0.2.dist-info/entry_points.txt
s3docker-2.0.2.dist-info/top_level.txt
s3docker-2.0.2.dist-info/RECORD
