Metadata-Version: 2.1
Name: s3docker
Version: 2.0.2
Summary: A tool to manage Docker images using S3 storage
Home-page: https://github.com/Kawai-Senpai/s3Docker
Author: Ranit Bhowmick
Author-email: bhowmickranitking@duck.com
License: MIT
Requires-Python: >=3.6
License-File: LICENSE.rst
Requires-Dist: boto3==1.34.106
Requires-Dist: docker==7.1.0
Requires-Dist: click==8.1.8
Requires-Dist: ultraprint>=3.1.0
Requires-Dist: tqdm>=4.65.0
Requires-Dist: halo>=0.0.31
